pyquo/__init__.py
pyquo/authenticator.py
pyquo/base.py
pyquo/errors.py
pyquo/fields.py
pyquo/helper.py
pyquo/magicparser.py
pyquo/models.py
pyquo/session.py
pyquo-20.1.5.dist-info/LICENSE
pyquo-20.1.5.dist-info/METADATA
pyquo-20.1.5.dist-info/WHEEL
pyquo-20.1.5.dist-info/top_level.txt
pyquo-20.1.5.dist-info/RECORD
