Metadata-Version: 2.1
Name: pyquo
Version: 20.1.5
Summary: Python QuoLab REST Client
Home-page: https://github.com/quolab/pyquo
Author: QuoLab Technologies
Author-email: curious@quolab.com
License: UNKNOWN
Platform: UNKNOWN
Requires-Dist: certifi (==2018.8.24)
Requires-Dist: chardet (==3.0.4)
Requires-Dist: idna (==2.6)
Requires-Dist: requests (==2.21.0)
Requires-Dist: six (==1.12.0)
Requires-Dist: urllib3 (==1.24.2)
